anansi/__init__.py
anansi/ansi.py
anansi/tags.py
anansi_tags-1.0.0.dist-info/METADATA
anansi_tags-1.0.0.dist-info/WHEEL
anansi_tags-1.0.0.dist-info/licenses/LICENSE
anansi_tags-1.0.0.dist-info/RECORD
